fedrq/__init__.py
fedrq/__main__.py
fedrq/_archive.py
fedrq/_compat.py
fedrq/_config.py
fedrq/_utils.py
fedrq/config.py
fedrq/py.typed
fedrq/release_repo.py
fedrq/repoquery.py
fedrq/backends/__init__.py
fedrq/backends/base/__init__.py
fedrq/backends/base/experimental.py
fedrq/backends/dnf/__init__.py
fedrq/backends/dnf/backend/__init__.py
fedrq/backends/dnf/backend/experimental.py
fedrq/backends/libdnf5/__init__.py
fedrq/backends/libdnf5/backend/__init__.py
fedrq/backends/libdnf5/backend/experimental.py
fedrq/cli/__init__.py
fedrq/cli/base.py
fedrq/cli/formatters.py
fedrq/cli/commands/COMMAND.py.in
fedrq/cli/commands/__init__.py
fedrq/cli/commands/cache.py
fedrq/cli/commands/changelogs.py
fedrq/cli/commands/download.py
fedrq/cli/commands/formatters.py
fedrq/cli/commands/pkgs.py
fedrq/cli/commands/repolist.py
fedrq/cli/commands/subpkgs.py
fedrq/cli/commands/whatrequires.py
fedrq/data/__init__.py
fedrq/data/releases.toml
fedrq/data/repos/__init__.py
fedrq/data/repos/almalinux.repo
fedrq/data/repos/amazonlinux.repo
fedrq/data/repos/centos-stream-compose.repo
fedrq/data/repos/centos-stream.repo
fedrq/data/repos/centos-stream8-compose.repo
fedrq/data/repos/centos-stream8.repo
fedrq/data/repos/centos7.repo
fedrq/data/repos/eln-buildroot.repo
fedrq/data/repos/eln.repo
fedrq/data/repos/epel.repo
fedrq/data/repos/fedora-eln.repo
fedrq/data/repos/fedora-rawhide.repo
fedrq/data/repos/fedora-updates-testing.repo
fedrq/data/repos/fedora-updates.repo
fedrq/data/repos/fedora.repo
fedrq/data/repos/oraclelinux-8.repo
fedrq/data/repos/oraclelinux-9.repo
fedrq/data/repos/rawhide-buildroot.repo
fedrq/data/repos/rocky.repo
fedrq/data/repos/ubi.repo
fedrq-1.5.0.data/data/share/licenses/fedrq/GPL-2.0-or-later.txt
fedrq-1.5.0.data/data/share/licenses/fedrq/MIT.txt
fedrq-1.5.0.data/data/share/licenses/fedrq/PSF-2.0.txt
fedrq-1.5.0.data/data/share/licenses/fedrq/Unlicense.txt
fedrq-1.5.0.dist-info/entry_points.txt
fedrq-1.5.0.dist-info/WHEEL
fedrq-1.5.0.dist-info/METADATA
fedrq-1.5.0.dist-info/RECORD
