Metadata-Version: 2.4
Name: fedrq
Version: 1.5.0
Summary: fedrq is a tool to query the Fedora and EPEL repositories
Author-email: Maxwell G <gotmax@e.email>
Requires-Python: >=3.9
Classifier: License :: OSI Approved :: GNU General Public License v2 or later (GPLv2+)
Classifier: Programming Language :: Python :: 3
Classifier: Programming Language :: Python :: 3 :: Only
Classifier: Programming Language :: Python :: 3.9
Classifier: Programming Language :: Python :: 3.10
Classifier: Programming Language :: Python :: 3.11
Classifier: Programming Language :: Python :: 3.12
Classifier: Operating System :: POSIX :: Linux
Classifier: Development Status :: 5 - Production/Stable
Classifier: Typing :: Typed
Classifier: Environment :: Console
Requires-Dist: pydantic >= 1, < 3
Requires-Dist: tomli; python_version<'3.11'
Requires-Dist: requests
Requires-Dist: rpm
Requires-Dist: typing-extensions
Requires-Dist: ruff ; extra == "codeqa"
Requires-Dist: reuse >= 4 ; extra == "codeqa"
Requires-Dist: fedrq[codeqa] ; extra == "dev"
Requires-Dist: fedrq[doc] ; extra == "dev"
Requires-Dist: fedrq[formatters] ; extra == "dev"
Requires-Dist: fedrq[test] ; extra == "dev"
Requires-Dist: fedrq[typing] ; extra == "dev"
Requires-Dist: nox ; extra == "dev"
Requires-Dist: black ; extra == "doc"
Requires-Dist: griffe !=0.32.0, !=0.32.1 ; extra == "doc"
Requires-Dist: mkdocs ; extra == "doc"
Requires-Dist: mkdocs-exclude ; extra == "doc"
Requires-Dist: mkdocs-gen-files ; extra == "doc"
Requires-Dist: mkdocs-material ; extra == "doc"
Requires-Dist: mkdocstrings[python]>=0.18 ; extra == "doc"
Requires-Dist: releaserr ; extra == "doc"
Requires-Dist: black ; extra == "formatters"
Requires-Dist: isort !=5.13.0 ; extra == "formatters"
Requires-Dist: pytest ; extra == "test"
Requires-Dist: pytest-mock ; extra == "test"
Requires-Dist: tomli-w ; extra == "test"
Requires-Dist: argcomplete ; extra == "typing"
Requires-Dist: basedpyright ; extra == "typing"
Requires-Dist: click ; extra == "typing"
Requires-Dist: fedrq[test] ; extra == "typing"
Requires-Dist: mypy ; extra == "typing"
Requires-Dist: tomli-w ; extra == "typing"
Requires-Dist: types-requests ; extra == "typing"
Requires-Dist: typing_extensions ; extra == "typing"
Project-URL: Changelog, https://fedrq.gtmx.me/News
Project-URL: Homepage, https://fedrq.gtmx.me
Project-URL: Mailing List, https://lists.sr.ht/~gotmax23/fedrq
Project-URL: Source, https://git.sr.ht/~gotmax23/fedrq
Provides-Extra: codeqa
Provides-Extra: dev
Provides-Extra: doc
Provides-Extra: formatters
Provides-Extra: test
Provides-Extra: typing
